supergravity/__init__.py
supergravity/__main__.py
supergravity/mcp_config.json
supergravity/global_workflows/debug.md
supergravity/global_workflows/deploy.md
supergravity/global_workflows/document.md
supergravity/global_workflows/implement.md
supergravity/global_workflows/refactor.md
supergravity/global_workflows/review.md
supergravity/global_workflows/scaffold.md
supergravity/global_workflows/security.md
supergravity/global_workflows/test.md
supergravity/rules/code-quality.md
supergravity/rules/security.md
supergravity/rules/supergravity.md
supergravity/setup/__init__.py
supergravity/setup/cli/__init__.py
supergravity/setup/cli/commands/__init__.py
supergravity/setup/services/__init__.py
supergravity/setup/services/config.py
supergravity/setup/services/installer.py
supergravity/setup/services/mcp_installer.py
supergravity/setup/services/mcp_registry.py
supergravity/setup/utils/__init__.py
supergravity/setup/utils/paths.py
supergravity-1.0.0.dist-info/licenses/LICENSE
supergravity-1.0.0.dist-info/METADATA
supergravity-1.0.0.dist-info/WHEEL
supergravity-1.0.0.dist-info/entry_points.txt
supergravity-1.0.0.dist-info/top_level.txt
supergravity-1.0.0.dist-info/RECORD
