Metadata-Version: 2.4
Name: supergravity
Version: 1.0.0
Summary: Framework for Google Antigravity IDE - Workflows, Rules, and MCP Configurations
Author-email: Mithun Gowda B <mithungowda.b7411@gmail.com>
Maintainer-email: Mithun Gowda B <mithungowda.b7411@gmail.com>
License: MIT
Project-URL: Homepage, https://github.com/mithun50/SuperGravity
Project-URL: Repository, https://github.com/mithun50/SuperGravity
Project-URL: Documentation, https://github.com/mithun50/SuperGravity#readme
Project-URL: Issues, https://github.com/mithun50/SuperGravity/issues
Keywords: antigravity,google,ide,ai,gemini,mcp,workflows,development,automation
Classifier: Development Status :: 4 - Beta
Classifier: Environment :: Console
Classifier: Intended Audience :: Developers
Classifier: License :: OSI Approved :: MIT License
Classifier: Operating System :: OS Independent
Classifier: Programming Language :: Python :: 3
Classifier: Programming Language :: Python :: 3.8
Classifier: Programming Language :: Python :: 3.9
Classifier: Programming Language :: Python :: 3.10
Classifier: Programming Language :: Python :: 3.11
Classifier: Programming Language :: Python :: 3.12
Classifier: Topic :: Software Development :: Libraries :: Python Modules
Classifier: Topic :: Text Editors :: Integrated Development Environments (IDE)
Requires-Python: >=3.8
License-File: LICENSE
Requires-Dist: click>=8.0.0
Requires-Dist: rich>=10.0.0
Requires-Dist: pyyaml>=6.0
Requires-Dist: pathlib>=1.0.1; python_version < "3.4"
Provides-Extra: dev
Requires-Dist: pytest>=7.0.0; extra == "dev"
Requires-Dist: pytest-cov>=4.0.0; extra == "dev"
Requires-Dist: black>=23.0.0; extra == "dev"
Requires-Dist: isort>=5.0.0; extra == "dev"
Requires-Dist: mypy>=1.0.0; extra == "dev"
Dynamic: license-file
